mod_log.py
MC/__init__.py
MC/World/__init__.py
MC/World/EntityManager/EntityManager.py
MC/World/EntityManager/__init__.py
Meta/ClassMetaManager.py
Meta/EnumMeta.py
Meta/PropertyObject.py
Meta/TypeMeta.py
Meta/__init__.py
Preset/__init__.py
Preset/Controller/PresetApi.py
Preset/Controller/__init__.py
Preset/Model/BoxData.py
Preset/Model/GameObject.py
Preset/Model/PartBase.py
Preset/Model/PresetBase.py
Preset/Model/PresetDataMeta.py
Preset/Model/SdkInterface.py
Preset/Model/Transform.py
Preset/Model/TransformObject.py
Preset/Model/__init__.py
Preset/Model/Block/BlockPreset.py
Preset/Model/Block/__init__.py
Preset/Model/Effect/EffectObject.py
Preset/Model/Effect/EffectPreset.py
Preset/Model/Effect/__init__.py
Preset/Model/Entity/EntityObject.py
Preset/Model/Entity/EntityPreset.py
Preset/Model/Entity/__init__.py
Preset/Model/Player/PlayerObject.py
Preset/Model/Player/PlayerPreset.py
Preset/Model/Player/__init__.py
Preset/Model/Textboard/TextboardObject.py
Preset/Model/Textboard/TextboardPreset.py
Preset/Model/Textboard/__init__.py
Preset/Model/UI/UIPreset.py
Preset/Model/UI/__init__.py
apolloCommon/__init__.py
apolloCommon/commonNetgameApi.py
apolloCommon/extraMongoPool.py
apolloCommon/extraMysqlPool.py
apolloCommon/extraRedisPool.py
apolloCommon/launcherApi.py
apolloCommon/mongoPool.py
apolloCommon/mysqlPool.py
apolloCommon/redisPool.py
apolloCommon/workerPool.py
bg/__init__.py
bg_mc_sdk-3.3.0.58879.dist-info/licenses/LICENSE
lobby/__init__.py
lobby/netgameApi.py
lobbyGame/__init__.py
lobbyGame/netgameApi.py
lobbyGame/serverEvent.py
master/__init__.py
master/masterHttp.py
master/netgameApi.py
master/serverEvent.py
master/serverManager.py
mod/__init__.py
mod/client/__init__.py
mod/client/clientEvent.py
mod/client/extraClientApi.py
mod/client/component/__init__.py
mod/client/component/achievementCompClient.py
mod/client/component/actionCompClient.py
mod/client/component/actorMotionCompClient.py
mod/client/component/actorRenderCompClient.py
mod/client/component/attrCompClient.py
bg_mc_sdk-3.3.0.58879.dist-info/METADATA
bg_mc_sdk-3.3.0.58879.dist-info/WHEEL
bg_mc_sdk-3.3.0.58879.dist-info/top_level.txt
bg_mc_sdk-3.3.0.58879.dist-info/RECORD
