Metadata-Version: 2.4
Name: bg_mc_sdk
Version: 3.3.0.58879
Summary: 一个用于python3的mc_sdk补全库
Author-email: classmate_chen <c_l-m@qq.com>
Project-URL: GitHub, https://github.com/cluom/bg_mc_sdk
Keywords: mc,minecraft,netease,mc-netease-sdk
Requires-Python: >=3.0
License-File: LICENSE
Dynamic: license-file
